cs2_battle_bot_api_client/__init__.py
cs2_battle_bot_api_client/api/__init__.py
cs2_battle_bot_api_client/api/account_connect_link/__init__.py
cs2_battle_bot_api_client/api/account_connect_link/account_connect_link_retrieve.py
cs2_battle_bot_api_client/api/discord_users/__init__.py
cs2_battle_bot_api_client/api/discord_users/discord_users_create.py
cs2_battle_bot_api_client/api/discord_users/discord_users_destroy.py
cs2_battle_bot_api_client/api/discord_users/discord_users_list.py
cs2_battle_bot_api_client/api/discord_users/discord_users_partial_update.py
cs2_battle_bot_api_client/api/discord_users/discord_users_retrieve.py
cs2_battle_bot_api_client/api/discord_users/discord_users_update.py
cs2_battle_bot_api_client/api/guilds/__init__.py
cs2_battle_bot_api_client/api/guilds/guilds_create.py
cs2_battle_bot_api_client/api/guilds/guilds_destroy.py
cs2_battle_bot_api_client/api/guilds/guilds_list.py
cs2_battle_bot_api_client/api/guilds/guilds_partial_update.py
cs2_battle_bot_api_client/api/guilds/guilds_retrieve.py
cs2_battle_bot_api_client/api/guilds/guilds_update.py
cs2_battle_bot_api_client/api/maps/__init__.py
cs2_battle_bot_api_client/api/maps/maps_create.py
cs2_battle_bot_api_client/api/maps/maps_destroy.py
cs2_battle_bot_api_client/api/maps/maps_list.py
cs2_battle_bot_api_client/api/maps/maps_partial_update.py
cs2_battle_bot_api_client/api/maps/maps_retrieve.py
cs2_battle_bot_api_client/api/maps/maps_update.py
cs2_battle_bot_api_client/api/matches/__init__.py
cs2_battle_bot_api_client/api/matches/matches_ban_create.py
cs2_battle_bot_api_client/api/matches/matches_bans_list.py
cs2_battle_bot_api_client/api/matches/matches_config_retrieve.py
cs2_battle_bot_api_client/api/matches/matches_create.py
cs2_battle_bot_api_client/api/matches/matches_destroy.py
cs2_battle_bot_api_client/api/matches/matches_join_create.py
cs2_battle_bot_api_client/api/matches/matches_list.py
cs2_battle_bot_api_client/api/matches/matches_load_create.py
cs2_battle_bot_api_client-0.0.35.dist-info/METADATA
cs2_battle_bot_api_client-0.0.35.dist-info/WHEEL
cs2_battle_bot_api_client-0.0.35.dist-info/RECORD
